cookgame
