Metadata-Version: 2.1
Name: cookgame
Version: 0.4.4
Summary: power by coding-ai.cn
Home-page: https://github.com/piglite
Author: piglite
Author-email: piglite@vip.sina.com
License: UNKNOWN
Platform: UNKNOWN
Classifier: Programming Language :: Python :: 3
Classifier: License :: OSI Approved :: MIT License
Classifier: Operating System :: OS Independent
Requires-Python: >3
